jw_plotter/PlotImplementations.py
jw_plotter/__init__.py
jw_plotter/pyqt_live_plotter.py
jw_plotter/pyqt_liveplotter_creatorconnector.py
jw_plotter-0.0.2.dist-info/LICENSE
jw_plotter-0.0.2.dist-info/METADATA
jw_plotter-0.0.2.dist-info/WHEEL
jw_plotter-0.0.2.dist-info/top_level.txt
jw_plotter-0.0.2.dist-info/RECORD
