Metadata-Version: 2.1
Name: jw-plotter
Version: 0.0.2
Summary: A small python liveplotter using PyQtGraph
Home-page: https://github.com/JakobWe/JWPlotter
Author: Jakob Weimar
Author-email: jakob.weimar@gmx.de
Classifier: Programming Language :: Python :: 3
Classifier: License :: OSI Approved :: GNU General Public License v3 (GPLv3)
Classifier: Operating System :: OS Independent
Requires-Python: >=3.6
License-File: LICENSE
Requires-Dist: pyqtgraph (>=0.10.0)
